st2auth_mongodb_backend/__init__.py
st2auth_mongodb_backend/mongodb.py
tests/__init__.py
tests/unit/__init__.py
tests/unit/test_mongodb_backend.py
st2_auth_backend_mongodb-0.3.0.dist-info/LICENSE
st2_auth_backend_mongodb-0.3.0.dist-info/METADATA
st2_auth_backend_mongodb-0.3.0.dist-info/WHEEL
st2_auth_backend_mongodb-0.3.0.dist-info/entry_points.txt
st2_auth_backend_mongodb-0.3.0.dist-info/top_level.txt
st2_auth_backend_mongodb-0.3.0.dist-info/RECORD
