Metadata-Version: 2.1
Name: st2-auth-backend-mongodb
Version: 0.3.0
Summary: StackStorm authentication backend which reads credentials from a MongoDB collection.
Home-page: https://github.com/StackStorm/st2-auth-backend-mongodb
Author: StackStorm, Inc.
Author-email: info@stackstorm.com
License: Apache License (2.0)
Download-URL: https://github.com/StackStorm/st2-auth-backend-mongodb/tarball/master
Platform: Any
Classifier: Development Status :: 3 - Alpha
Classifier: License :: OSI Approved :: Apache Software License
Classifier: Programming Language :: Python
Classifier: Programming Language :: Python :: 3
Classifier: Programming Language :: Python :: 3.8
Classifier: Programming Language :: Python :: 3.9
Classifier: Programming Language :: Python :: 3.10
Classifier: Programming Language :: Python :: 3.11
Classifier: Intended Audience :: Developers
Classifier: Environment :: Console
Provides: st2auth_mongodb_backend
Requires-Python: >=3.8
Requires-Dist: pymongo<4.7,>=4.0.0
